gaftools/.gitignore
gaftools/__init__.py
gaftools/__main__.py
gaftools/_version.py
gaftools/args.py
gaftools/conversion.py
gaftools/gaf.py
gaftools/gfa.py
gaftools/timer.py
gaftools/utils.py
gaftools/cli/__init__.py
gaftools/cli/find_path.py
gaftools/cli/gfa2rgfa.py
gaftools/cli/index.py
gaftools/cli/order_gfa.py
gaftools/cli/phase.py
gaftools/cli/realign.py
gaftools/cli/sort.py
gaftools/cli/stat.py
gaftools/cli/view.py
gaftools-1.3.0.dist-info/licenses/LICENSE
gaftools-1.3.0.dist-info/METADATA
gaftools-1.3.0.dist-info/WHEEL
gaftools-1.3.0.dist-info/entry_points.txt
gaftools-1.3.0.dist-info/top_level.txt
gaftools-1.3.0.dist-info/RECORD
