Metadata-Version: 2.4
Name: gaftools
Version: 1.3.0
Summary: Toolkit for pangenome alignments
Author: Arda Soylev, Fawaz Dabbaghie, Tobias Marschall
Author-email: Samarendra Pani <samarendra.pani@hhu.de>
Maintainer-email: Samarendra Pani <samarendra.pani@hhu.de>
License-Expression: MIT
Project-URL: Homepage, https://github.com/marschall-lab/gaftools
Project-URL: Issues, https://github.com/marschall-lab/gaftools/issues
Project-URL: Changelog, https://github.com/marschall-lab/gaftools/blob/main/CHANGES.rst
Keywords: bioinformatics,genomics,pangenome,toolkit
Classifier: Development Status :: 4 - Beta
Classifier: Programming Language :: Python :: 3
Classifier: Operating System :: OS Independent
Classifier: Environment :: Console
Classifier: Intended Audience :: Science/Research
Classifier: Topic :: Scientific/Engineering :: Bio-Informatics
Requires-Python: >=3.9
License-File: LICENSE
Requires-Dist: pysam
Requires-Dist: pywfa==0.5.1
Provides-Extra: dev
Requires-Dist: pytest; extra == "dev"
Requires-Dist: coverage; extra == "dev"
Requires-Dist: tox; extra == "dev"
Requires-Dist: ruff; extra == "dev"
Requires-Dist: pre-commit; extra == "dev"
Requires-Dist: sphinx; extra == "dev"
Requires-Dist: sphinx-issues; extra == "dev"
Requires-Dist: sphinx-rtd-theme; extra == "dev"
Requires-Dist: sphinx-better-subsection; extra == "dev"
Requires-Dist: setuptools_scm; extra == "dev"
Provides-Extra: docs
Requires-Dist: sphinx; extra == "docs"
Requires-Dist: sphinx-rtd-theme; extra == "docs"
Requires-Dist: sphinx-issues; extra == "docs"
Requires-Dist: sphinx-better-subsection; extra == "docs"
Dynamic: license-file
Dynamic: requires-dist
